maths/__init__.py
maths/admin.py
maths/apps.py
maths/models.py
maths/service.py
maths/tests.py
maths/views.py
maths/migrations/__init__.py
project/__init__.py
project/asgi.py
project/settings.py
project/urls.py
project/wsgi.py
maths_service-0.1.0.dist-info/METADATA
maths_service-0.1.0.dist-info/WHEEL
maths_service-0.1.0.dist-info/top_level.txt
maths_service-0.1.0.dist-info/RECORD
